setup.py
jdOctopus/__init__.py
jdOctopus/index.py
jdOctopus/tool.py
jdOctopus.egg-info/PKG-INFO
jdOctopus.egg-info/SOURCES.txt
jdOctopus.egg-info/dependency_links.txt
jdOctopus.egg-info/not-zip-safe
jdOctopus.egg-info/top_level.txt
jdOctopus/model/__init__.py
jdOctopus/model/device.py
jdOctopus/model/img.py
jdOctopus/model/info.py
jdOctopus/model/point.py
jdOctopus/model/swipe.py
jdOctopus/model/text.py
jdOctopus/test/__init__.py
jdOctopus/test/test.py
jdOctopus/test/test2.py
jdOctopus/test/testReport.py