Metadata-Version: 1.0
Name: jdOctopus
Version: 0.4
Summary: jd-octopus py version
Home-page: http://dqa.jd.com/octopus
Author: renran
Author-email: 1114802403@qq.com
License: MIT
Platform: UNKNOWN
